visier/__init__.py
visier/sdk/__init__.py
visier/sdk/api/__init__.py
visier/sdk/api/administration/__init__.py
visier/sdk/api/administration/api_client.py
visier/sdk/api/administration/api_response.py
visier/sdk/api/administration/configuration.py
visier/sdk/api/administration/exceptions.py
visier/sdk/api/administration/py.typed
visier/sdk/api/administration/rest.py
visier/sdk/api/administration/api/__init__.py
visier/sdk/api/administration/api/consolidated_analytics_api.py
visier/sdk/api/administration/api/permissions_api.py
visier/sdk/api/administration/api/production_versions_api.py
visier/sdk/api/administration/api/profiles_api.py
visier/sdk/api/administration/api/projects_api.py
visier/sdk/api/administration/api/sources_api.py
visier/sdk/api/administration/api/system_status_api.py
visier/sdk/api/administration/api/tenants_v1_api.py
visier/sdk/api/administration/api/tenants_v2_api.py
visier/sdk/api/administration/api/user_groups_v2_api.py
visier/sdk/api/administration/api/users_v1_api.py
visier/sdk/api/administration/api/users_v2_api.py
visier/sdk/api/administration/models/__init__.py
visier/sdk/api/administration/models/accessible_tenant_profile_assignment_request_dto.py
visier/sdk/api/administration/models/accessible_tenant_profile_assignment_response_dto.py
visier/sdk/api/administration/models/accessible_tenant_profile_revoke_request_dto.py
visier/sdk/api/administration/models/accessible_tenant_profile_revoke_response_dto.py
visier/sdk/api/administration/models/additional_capabilities_dto.py
visier/sdk/api/administration/models/admin_capability_config_dto.py
visier/sdk/api/administration/models/all_permissions_assigned_for_local_tenant_dto.py
visier/sdk/api/administration/models/all_profile_assigned_for_accessible_tenant_dto.py
visier/sdk/api/administration/models/all_profile_assigned_for_local_tenant_dto.py
visier/sdk/api/administration/models/all_tenants_status_apidto.py
visier/sdk/api/administration/models/all_user_groups_assigned_for_local_tenant_dto.py
visier.sdk.api.administration-22222222.99201.1456.dist-info/METADATA
visier.sdk.api.administration-22222222.99201.1456.dist-info/WHEEL
visier.sdk.api.administration-22222222.99201.1456.dist-info/top_level.txt
visier.sdk.api.administration-22222222.99201.1456.dist-info/RECORD
